lonesum/__init__.py
lonesum-0.1.dist-info/LICENCE.txt
lonesum-0.1.dist-info/METADATA
lonesum-0.1.dist-info/WHEEL
lonesum-0.1.dist-info/top_level.txt
lonesum-0.1.dist-info/RECORD
