Metadata-Version: 2.1
Name: lonesum
Version: 0.1
Summary: This is lone sume program
Author: Saral Kumar kaviti
Author-email: saralkumar.kapilit@gmail.com
Classifier: Programming Language :: Python :: 3
Classifier: License :: OSI Approved :: MIT License
Classifier: Operating System :: OS Independent
License-File: LICENCE.txt
